optoanalysis/VERSION
optoanalysis/__init__.py
optoanalysis/optoanalysis.py
optoanalysis/widgetmultiplot.py
optoanalysis/LeCroy/LeCroy.py
optoanalysis/LeCroy/__init__.py
optoanalysis/Saleae/Saleae.py
optoanalysis/Saleae/__init__.py
optoanalysis/thermo/__init__.py
optoanalysis/thermo/thermo.py
optoanalysis-4.3.2.dist-info/LICENSE
optoanalysis-4.3.2.dist-info/METADATA
optoanalysis-4.3.2.dist-info/WHEEL
optoanalysis-4.3.2.dist-info/top_level.txt
optoanalysis-4.3.2.dist-info/RECORD
