Metadata-Version: 2.1
Name: optoanalysis
Version: 4.3.2
Summary: Python package with functions for data analysis
Home-page: https://github.com/AshleySetter/optoanalysis
Download-URL: https://github.com/AshleySetter/optoanalysis/archive/4.3.2.tar.gz
Author: Ashley Setter
Author-email: A.Setter@soton.ac.uk
License-File: LICENSE
Requires-Dist: numpy
Requires-Dist: scipy
Requires-Dist: llvmlite
Requires-Dist: matplotlib
Requires-Dist: seaborn
Requires-Dist: qplots (>=0.5)
Requires-Dist: frange (>=0.0.6)
Requires-Dist: uncertainties
Requires-Dist: pytest
Requires-Dist: pytest-cov
Requires-Dist: pytest-mpl
Requires-Dist: numpydoc
Requires-Dist: sphinx-rtd-theme
Requires-Dist: scikit-image
Requires-Dist: nptdms
Requires-Dist: pint
